cryptopay/__init__.py
cryptopay/enums/__init__.py
cryptopay/enums/status.py
cryptopay/interfaces/__init__.py
cryptopay/interfaces/blockchain_reader.py
cryptopay/interfaces/exchange_rate_provider.py
cryptopay/interfaces/exchange_rate_repository.py
cryptopay/interfaces/invoice_repository.py
cryptopay/interfaces/network_client.py
cryptopay/interfaces/security_provider.py
cryptopay/interfaces/transaction_repository.py
cryptopay/interfaces/wallet_repository.py
cryptopay/models/__init__.py
cryptopay/models/exchange_rate.py
cryptopay/models/invoice.py
cryptopay/models/transaction.py
cryptopay/models/wallet.py
cryptopay/models/wallet_credentials.py
cryptopay/repositories/__init__.py
cryptopay/repositories/exchange_rate/__init__.py
cryptopay/repositories/exchange_rate/in_memory_exchange_rate_repository.py
cryptopay/repositories/invoice/__init__.py
cryptopay/repositories/invoice/in_memory_invoice_repository.py
cryptopay/repositories/transaction/__init__.py
cryptopay/repositories/transaction/in_memory_transaction_repository.py
cryptopay/security/__init__.py
cryptopay/security/fernet_security_provider.py
pay_with_crypto-0.2.0.dist-info/LICENSE
pay_with_crypto-0.2.0.dist-info/METADATA
pay_with_crypto-0.2.0.dist-info/WHEEL
pay_with_crypto-0.2.0.dist-info/RECORD
