Metadata-Version: 2.3
Name: pay-with-crypto
Version: 0.2.0
Summary: A Python library for handling cryptocurrency payments.
License: MIT
Keywords: crypto,payment,blockchain,invoice,wallet
Author: kirillketrik
Author-email: kirillketrik34@gmail.com
Requires-Python: >=3.12,<4.0
Classifier: Development Status :: 3 - Alpha
Classifier: Intended Audience :: Developers
Classifier: License :: OSI Approved :: MIT License
Classifier: Operating System :: OS Independent
Classifier: Programming Language :: Python :: 3
Classifier: Programming Language :: Python :: 3.12
Classifier: Programming Language :: Python :: 3.13
Requires-Dist: cryptography (>=45.0.7,<46.0.0)
Requires-Dist: pydantic (>=2.11.9,<3.0.0)
Project-URL: Homepage, https://github.com/kirillketrik/pay-with-crypto
Project-URL: Repository, https://github.com/kirillketrik/pay-with-crypto
